cardkb/__init__.py
cardkb/__main__.py
cardkb/ascii_codes.py
cardkb/keys.py
cardkb-1.0.0.dist-info/METADATA
cardkb-1.0.0.dist-info/WHEEL
cardkb-1.0.0.dist-info/entry_points.txt
cardkb-1.0.0.dist-info/top_level.txt
cardkb-1.0.0.dist-info/RECORD
