Metadata-Version: 2.4
Name: cardkb
Version: 1.0.0
Summary: Driver for M5Stack CardKB (I2C mini keyboard) on Raspberry Pi
Author-email: Ian King <hello@antking.co>
License: MIT
Project-URL: Homepage, https://github.com/ian-antking/cardkb
Project-URL: Issues, https://github.com/ian-antking/cardkb/issues
Requires-Python: >=3.7
Requires-Dist: python-uinput
Requires-Dist: smbus2
